Gender_Predictor-0.5.dist-info/DESCRIPTION.rst
Gender_Predictor-0.5.dist-info/METADATA
Gender_Predictor-0.5.dist-info/RECORD
Gender_Predictor-0.5.dist-info/WHEEL
Gender_Predictor-0.5.dist-info/metadata.json
Gender_Predictor-0.5.dist-info/top_level.txt
gender_predictor/GenderClassifier.py
gender_predictor/GenderLoader.py
gender_predictor/__init__.py
gender_predictor/data/gender_type.csv
