Metadata-Version: 2.0
Name: Gender-Predictor
Version: 0.5
Summary: Classify the name based on given name
Home-page: https://github.com/jiteshmohite/Gender-Predictor
Author: Mustafa Atik
Author-email: muatik@gmail.com
License: UNKNOWN
Platform: UNKNOWN
Requires-Dist: nltk
